[
  {
    "game_id": "401705307",
    "date": "2025-02-08T20:00:00.000Z",
    "season_year": 2025,
    "season_type": 2,
    "status": "STATUS_SCHEDULED",
    "home_team_id": "6",
    "home_team_name": "Mavericks",
    "home_team_score": 0,
    "away_team_id": "10",
    "away_team_name": "Rockets",
    "away_team_score": 0,
    "home_rebounds": 44.2,
    "home_assists": 25.6,
    "home_fieldGoalsAttempted": 91.8,
    "home_fieldGoalsMade": 43.6,
    "home_fieldGoalPct": 0.4766,
    "home_freeThrowsAttempted": 20.4,
    "home_freeThrowsMade": 16.2,
    "home_freeThrowPct": 0.7918,
    "home_threePointFieldGoalsAttempted": 37.0,
    "home_threePointFieldGoalsMade": 13.2,
    "home_threePointPct": 0.359,
    "home_overall_record": "27-25",
    "home_home_record": "14-10",
    "home_road_record": "13-15",
    "home_overall_record_win_rate": 0.519,
    "home_home_record_win_rate": 0.583,
    "home_road_record_win_rate": 0.464,
    "home_recent_win_rate": 0.3333333333,
    "home_recent_avg_score": 114.67,
    "home_recent_home_win_rate": 0.0,
    "home_recent_away_win_rate": 0.3333333333,
    "home_leader_points": 26.6,
    "home_leader_rebounds": 12.4,
    "home_leader_assists": 5.6,
    "home_rest_days": 0.0,
    "away_rebounds": 44.6,
    "away_assists": 23.2,
    "away_fieldGoalsAttempted": 92.6,
    "away_fieldGoalsMade": 40.6,
    "away_fieldGoalPct": 0.4386,
    "away_freeThrowsAttempted": 22.6,
    "away_freeThrowsMade": 16.8,
    "away_freeThrowPct": 0.7534,
    "away_threePointFieldGoalsAttempted": 32.4,
    "away_threePointFieldGoalsMade": 11.2,
    "away_threePointPct": 0.3462,
    "away_overall_record": "32-19",
    "away_home_record": "15-8",
    "away_road_record": "17-11",
    "away_overall_record_win_rate": 0.627,
    "away_home_record_win_rate": 0.652,
    "away_road_record_win_rate": 0.607,
    "away_recent_win_rate": 0.0,
    "away_recent_avg_score": 109.67,
    "away_recent_home_win_rate": 0.0,
    "away_recent_away_win_rate": 0.0,
    "away_leader_points": 26.2,
    "away_leader_rebounds": 13.0,
    "away_leader_assists": 7.6,
    "away_rest_days": 0.0,
    "home_vs_away_wins": 0.0,
    "home_vs_away_losses": 1.0,
    "home_vs_away_win_rate": 0.0
  },
  {
    "game_id": "401705308",
    "date": "2025-02-08T21:00:00.000Z",
    "season_year": 2025,
    "season_type": 2,
    "status": "STATUS_SCHEDULED",
    "home_team_id": "13",
    "home_team_name": "Lakers",
    "home_team_score": 0,
    "away_team_id": "11",
    "away_team_name": "Pacers",
    "away_team_score": 0,
    "home_rebounds": 44.2,
    "home_assists": 28.2,
    "home_fieldGoalsAttempted": 80.4,
    "home_fieldGoalsMade": 43.4,
    "home_fieldGoalPct": 0.5388,
    "home_freeThrowsAttempted": 24.4,
    "home_freeThrowsMade": 19.8,
    "home_freeThrowPct": 0.8146,
    "home_threePointFieldGoalsAttempted": 35.4,
    "home_threePointFieldGoalsMade": 15.0,
    "home_threePointPct": 0.4208,
    "home_overall_record": "30-19",
    "home_home_record": "17-6",
    "home_road_record": "13-13",
    "home_overall_record_win_rate": 0.612,
    "home_home_record_win_rate": 0.739,
    "home_road_record_win_rate": 0.5,
    "home_recent_win_rate": 1.0,
    "home_recent_avg_score": 123.33,
    "home_recent_home_win_rate": 1.0,
    "home_recent_away_win_rate": 1.0,
    "home_leader_points": 31.2,
    "home_leader_rebounds": 10.8,
    "home_leader_assists": 9.8,
    "home_rest_days": 0.0,
    "away_rebounds": 39.8,
    "away_assists": 30.2,
    "away_fieldGoalsAttempted": 87.6,
    "away_fieldGoalsMade": 43.0,
    "away_fieldGoalPct": 0.4916,
    "away_freeThrowsAttempted": 24.2,
    "away_freeThrowsMade": 19.2,
    "away_freeThrowPct": 0.797,
    "away_threePointFieldGoalsAttempted": 35.2,
    "away_threePointFieldGoalsMade": 11.8,
    "away_threePointPct": 0.3286,
    "away_overall_record": "29-21",
    "away_home_record": "14-8",
    "away_road_record": "15-13",
    "away_overall_record_win_rate": 0.58,
    "away_home_record_win_rate": 0.636,
    "away_road_record_win_rate": 0.536,
    "away_recent_win_rate": 0.6666666667,
    "away_recent_avg_score": 106.67,
    "away_recent_home_win_rate": 0.0,
    "away_recent_away_win_rate": 0.6666666667,
    "away_leader_points": 25.8,
    "away_leader_rebounds": 8.2,
    "away_leader_assists": 7.8,
    "away_rest_days": 0.0,
    "home_vs_away_wins": 0.0,
    "home_vs_away_losses": 0.0,
    "home_vs_away_win_rate": 0.5
  },
  {
    "game_id": "401705309",
    "date": "2025-02-09T00:00:00.000Z",
    "season_year": 2025,
    "season_type": 2,
    "status": "STATUS_SCHEDULED",
    "home_team_id": "19",
    "home_team_name": "Magic",
    "home_team_score": 0,
    "away_team_id": "24",
    "away_team_name": "Spurs",
    "away_team_score": 0,
    "home_rebounds": 40.6,
    "home_assists": 21.4,
    "home_fieldGoalsAttempted": 88.6,
    "home_fieldGoalsMade": 37.6,
    "home_fieldGoalPct": 0.4242,
    "home_freeThrowsAttempted": 22.0,
    "home_freeThrowsMade": 17.8,
    "home_freeThrowPct": 0.7814,
    "home_threePointFieldGoalsAttempted": 32.2,
    "home_threePointFieldGoalsMade": 8.6,
    "home_threePointPct": 0.2678,
    "home_overall_record": "25-28",
    "home_home_record": "15-9",
    "home_road_record": "10-19",
    "home_overall_record_win_rate": 0.472,
    "home_home_record_win_rate": 0.625,
    "home_road_record_win_rate": 0.345,
    "home_recent_win_rate": 0.3333333333,
    "home_recent_avg_score": 106.33,
    "home_recent_home_win_rate": 0.0,
    "home_recent_away_win_rate": 0.3333333333,
    "home_leader_points": 27.4,
    "home_leader_rebounds": 9.0,
    "home_leader_assists": 5.8,
    "home_rest_days": 1.0,
    "away_rebounds": 45.6,
    "away_assists": 31.2,
    "away_fieldGoalsAttempted": 95.4,
    "away_fieldGoalsMade": 44.4,
    "away_fieldGoalPct": 0.4642,
    "away_freeThrowsAttempted": 21.2,
    "away_freeThrowsMade": 16.4,
    "away_freeThrowPct": 0.7694,
    "away_threePointFieldGoalsAttempted": 39.6,
    "away_threePointFieldGoalsMade": 14.4,
    "away_threePointPct": 0.3556,
    "away_overall_record": "22-27",
    "away_home_record": "13-12",
    "away_road_record": "8-14",
    "away_overall_record_win_rate": 0.449,
    "away_home_record_win_rate": 0.52,
    "away_road_record_win_rate": 0.364,
    "away_recent_win_rate": 0.3333333333,
    "away_recent_avg_score": 117.0,
    "away_recent_home_win_rate": 0.0,
    "away_recent_away_win_rate": 0.3333333333,
    "away_leader_points": 26.6,
    "away_leader_rebounds": 12.6,
    "away_leader_assists": 8.8,
    "away_rest_days": 0.0,
    "home_vs_away_wins": 0.0,
    "home_vs_away_losses": 0.0,
    "home_vs_away_win_rate": 0.5
  },
  {
    "game_id": "401705310",
    "date": "2025-02-09T00:00:00.000Z",
    "season_year": 2025,
    "season_type": 2,
    "status": "STATUS_SCHEDULED",
    "home_team_id": "27",
    "home_team_name": "Wizards",
    "home_team_score": 0,
    "away_team_id": "1",
    "away_team_name": "Hawks",
    "away_team_score": 0,
    "home_rebounds": 43.2,
    "home_assists": 27.6,
    "home_fieldGoalsAttempted": 89.6,
    "home_fieldGoalsMade": 40.2,
    "home_fieldGoalPct": 0.4506,
    "home_freeThrowsAttempted": 22.6,
    "home_freeThrowsMade": 17.6,
    "home_freeThrowPct": 0.78,
    "home_threePointFieldGoalsAttempted": 43.0,
    "home_threePointFieldGoalsMade": 15.6,
    "home_threePointPct": 0.3688,
    "home_overall_record": "9-42",
    "home_home_record": "5-21",
    "home_road_record": "4-21",
    "home_overall_record_win_rate": 0.176,
    "home_home_record_win_rate": 0.192,
    "home_road_record_win_rate": 0.16,
    "home_recent_win_rate": 0.6666666667,
    "home_recent_avg_score": 122.33,
    "home_recent_home_win_rate": 0.0,
    "home_recent_away_win_rate": 1.0,
    "home_leader_points": 28.0,
    "home_leader_rebounds": 10.8,
    "home_leader_assists": 6.8,
    "home_rest_days": 0.0,
    "away_rebounds": 42.8,
    "away_assists": 29.6,
    "away_fieldGoalsAttempted": 88.8,
    "away_fieldGoalsMade": 44.2,
    "away_fieldGoalPct": 0.4982,
    "away_freeThrowsAttempted": 26.8,
    "away_freeThrowsMade": 20.0,
    "away_freeThrowPct": 0.734,
    "away_threePointFieldGoalsAttempted": 38.2,
    "away_threePointFieldGoalsMade": 14.4,
    "away_threePointPct": 0.377,
    "away_overall_record": "24-28",
    "away_home_record": "12-12",
    "away_road_record": "12-16",
    "away_overall_record_win_rate": 0.462,
    "away_home_record_win_rate": 0.5,
    "away_road_record_win_rate": 0.429,
    "away_recent_win_rate": 0.6666666667,
    "away_recent_avg_score": 124.0,
    "away_recent_home_win_rate": 0.5,
    "away_recent_away_win_rate": 1.0,
    "away_leader_points": 30.8,
    "away_leader_rebounds": 10.4,
    "away_leader_assists": 11.6,
    "away_rest_days": 0.0,
    "home_vs_away_wins": 0.0,
    "home_vs_away_losses": 1.0,
    "home_vs_away_win_rate": 0.0
  },
  {
    "game_id": "401705311",
    "date": "2025-02-09T01:00:00.000Z",
    "season_year": 2025,
    "season_type": 2,
    "status": "STATUS_SCHEDULED",
    "home_team_id": "4",
    "home_team_name": "Bulls",
    "home_team_score": 0,
    "away_team_id": "9",
    "away_team_name": "Warriors",
    "away_team_score": 0,
    "home_rebounds": 44.0,
    "home_assists": 30.0,
    "home_fieldGoalsAttempted": 88.8,
    "home_fieldGoalsMade": 42.2,
    "home_fieldGoalPct": 0.4756,
    "home_freeThrowsAttempted": 18.6,
    "home_freeThrowsMade": 15.4,
    "home_freeThrowPct": 0.8372,
    "home_threePointFieldGoalsAttempted": 43.6,
    "home_threePointFieldGoalsMade": 16.6,
    "home_threePointPct": 0.3834,
    "home_overall_record": "22-30",
    "home_home_record": "10-16",
    "home_road_record": "12-14",
    "home_overall_record_win_rate": 0.423,
    "home_home_record_win_rate": 0.385,
    "home_road_record_win_rate": 0.462,
    "home_recent_win_rate": 0.3333333333,
    "home_recent_avg_score": 120.0,
    "home_recent_home_win_rate": 1.0,
    "home_recent_away_win_rate": 0.0,
    "home_leader_points": 21.4,
    "home_leader_rebounds": 11.2,
    "home_leader_assists": 7.8,
    "home_rest_days": 2.0,
    "away_rebounds": 43.2,
    "away_assists": 28.6,
    "away_fieldGoalsAttempted": 91.2,
    "away_fieldGoalsMade": 39.4,
    "away_fieldGoalPct": 0.4342,
    "away_freeThrowsAttempted": 26.8,
    "away_freeThrowsMade": 19.4,
    "away_freeThrowPct": 0.7222,
    "away_threePointFieldGoalsAttempted": 44.4,
    "away_threePointFieldGoalsMade": 14.8,
    "away_threePointPct": 0.334,
    "away_overall_record": "25-26",
    "away_home_record": "15-13",
    "away_road_record": "10-13",
    "away_overall_record_win_rate": 0.49,
    "away_home_record_win_rate": 0.536,
    "away_road_record_win_rate": 0.435,
    "away_recent_win_rate": 0.3333333333,
    "away_recent_avg_score": 114.67,
    "away_recent_home_win_rate": 1.0,
    "away_recent_away_win_rate": 0.0,
    "away_leader_points": 27.6,
    "away_leader_rebounds": 10.0,
    "away_leader_assists": 7.0,
    "away_rest_days": 1.0,
    "home_vs_away_wins": 0.0,
    "home_vs_away_losses": 1.0,
    "home_vs_away_win_rate": 0.0
  },
  {
    "game_id": "401705312",
    "date": "2025-02-09T01:00:00.000Z",
    "season_year": 2025,
    "season_type": 2,
    "status": "STATUS_SCHEDULED",
    "home_team_id": "29",
    "home_team_name": "Grizzlies",
    "home_team_score": 0,
    "away_team_id": "25",
    "away_team_name": "Thunder",
    "away_team_score": 0,
    "home_rebounds": 50.6,
    "home_assists": 27.2,
    "home_fieldGoalsAttempted": 95.8,
    "home_fieldGoalsMade": 47.2,
    "home_fieldGoalPct": 0.4932,
    "home_freeThrowsAttempted": 23.4,
    "home_freeThrowsMade": 18.0,
    "home_freeThrowPct": 0.781,
    "home_threePointFieldGoalsAttempted": 33.0,
    "home_threePointFieldGoalsMade": 12.4,
    "home_threePointPct": 0.373,
    "home_overall_record": "35-16",
    "home_home_record": "21-5",
    "home_road_record": "14-11",
    "home_overall_record_win_rate": 0.686,
    "home_home_record_win_rate": 0.808,
    "home_road_record_win_rate": 0.56,
    "home_recent_win_rate": 1.0,
    "home_recent_avg_score": 132.67,
    "home_recent_home_win_rate": 1.0,
    "home_recent_away_win_rate": 1.0,
    "home_leader_points": 29.0,
    "home_leader_rebounds": 12.6,
    "home_leader_assists": 7.6,
    "home_rest_days": 2.0,
    "away_rebounds": 53.0,
    "away_assists": 27.2,
    "away_fieldGoalsAttempted": 98.2,
    "away_fieldGoalsMade": 48.6,
    "away_fieldGoalPct": 0.4948,
    "away_freeThrowsAttempted": 21.4,
    "away_freeThrowsMade": 17.6,
    "away_freeThrowPct": 0.8182,
    "away_threePointFieldGoalsAttempted": 39.8,
    "away_threePointFieldGoalsMade": 13.0,
    "away_threePointPct": 0.322,
    "away_overall_record": "41-9",
    "away_home_record": "24-3",
    "away_road_record": "17-6",
    "away_overall_record_win_rate": 0.82,
    "away_home_record_win_rate": 0.889,
    "away_road_record_win_rate": 0.739,
    "away_recent_win_rate": 1.0,
    "away_recent_avg_score": 128.67,
    "away_recent_home_win_rate": 1.0,
    "away_recent_away_win_rate": 0.0,
    "away_leader_points": 40.8,
    "away_leader_rebounds": 12.6,
    "away_leader_assists": 6.4,
    "away_rest_days": 0.0,
    "home_vs_away_wins": 0.0,
    "home_vs_away_losses": 1.0,
    "home_vs_away_win_rate": 0.0
  },
  {
    "game_id": "401705313",
    "date": "2025-02-09T01:00:00.000Z",
    "season_year": 2025,
    "season_type": 2,
    "status": "STATUS_SCHEDULED",
    "home_team_id": "16",
    "home_team_name": "Timberwolves",
    "home_team_score": 0,
    "away_team_id": "22",
    "away_team_name": "Trail Blazers",
    "away_team_score": 0,
    "home_rebounds": 45.6,
    "home_assists": 29.0,
    "home_fieldGoalsAttempted": 92.2,
    "home_fieldGoalsMade": 43.4,
    "home_fieldGoalPct": 0.4744,
    "home_freeThrowsAttempted": 22.0,
    "home_freeThrowsMade": 18.8,
    "home_freeThrowPct": 0.8642,
    "home_threePointFieldGoalsAttempted": 40.8,
    "home_threePointFieldGoalsMade": 16.2,
    "home_threePointPct": 0.3978,
    "home_overall_record": "29-23",
    "home_home_record": "14-12",
    "home_road_record": "15-11",
    "home_overall_record_win_rate": 0.558,
    "home_home_record_win_rate": 0.538,
    "home_road_record_win_rate": 0.577,
    "home_recent_win_rate": 0.6666666667,
    "home_recent_avg_score": 122.67,
    "home_recent_home_win_rate": 0.6666666667,
    "home_recent_away_win_rate": 0.0,
    "home_leader_points": 35.8,
    "home_leader_rebounds": 12.8,
    "home_leader_assists": 8.4,
    "home_rest_days": 1.0,
    "away_rebounds": 45.4,
    "away_assists": 25.0,
    "away_fieldGoalsAttempted": 87.6,
    "away_fieldGoalsMade": 41.4,
    "away_fieldGoalPct": 0.4742,
    "away_freeThrowsAttempted": 25.4,
    "away_freeThrowsMade": 21.2,
    "away_freeThrowPct": 0.8394,
    "away_threePointFieldGoalsAttempted": 34.6,
    "away_threePointFieldGoalsMade": 13.4,
    "away_threePointPct": 0.3896,
    "away_overall_record": "23-29",
    "away_home_record": "15-13",
    "away_road_record": "8-16",
    "away_overall_record_win_rate": 0.442,
    "away_home_record_win_rate": 0.536,
    "away_road_record_win_rate": 0.333,
    "away_recent_win_rate": 1.0,
    "away_recent_avg_score": 113.67,
    "away_recent_home_win_rate": 1.0,
    "away_recent_away_win_rate": 0.0,
    "away_leader_points": 24.8,
    "away_leader_rebounds": 12.6,
    "away_leader_assists": 8.2,
    "away_rest_days": 1.0,
    "home_vs_away_wins": 1.0,
    "home_vs_away_losses": 2.0,
    "home_vs_away_win_rate": 0.3333333333
  },
  {
    "game_id": "401705314",
    "date": "2025-02-09T01:30:00.000Z",
    "season_year": 2025,
    "season_type": 2,
    "status": "STATUS_SCHEDULED",
    "home_team_id": "18",
    "home_team_name": "Knicks",
    "home_team_score": 0,
    "away_team_id": "2",
    "away_team_name": "Celtics",
    "away_team_score": 0,
    "home_rebounds": 41.6,
    "home_assists": 29.6,
    "home_fieldGoalsAttempted": 96.6,
    "home_fieldGoalsMade": 48.4,
    "home_fieldGoalPct": 0.5006,
    "home_freeThrowsAttempted": 21.6,
    "home_freeThrowsMade": 16.6,
    "home_freeThrowPct": 0.7616,
    "home_threePointFieldGoalsAttempted": 31.4,
    "home_threePointFieldGoalsMade": 11.0,
    "home_threePointPct": 0.3412,
    "home_overall_record": "34-17",
    "home_home_record": "18-9",
    "home_road_record": "16-8",
    "home_overall_record_win_rate": 0.667,
    "home_home_record_win_rate": 0.667,
    "home_road_record_win_rate": 0.667,
    "home_recent_win_rate": 0.6666666667,
    "home_recent_avg_score": 119.0,
    "home_recent_home_win_rate": 0.5,
    "home_recent_away_win_rate": 1.0,
    "home_leader_points": 30.8,
    "home_leader_rebounds": 13.0,
    "home_leader_assists": 9.6,
    "home_rest_days": 3.0,
    "away_rebounds": 42.2,
    "away_assists": 30.8,
    "away_fieldGoalsAttempted": 88.4,
    "away_fieldGoalsMade": 42.2,
    "away_fieldGoalPct": 0.4792,
    "away_freeThrowsAttempted": 20.4,
    "away_freeThrowsMade": 16.0,
    "away_freeThrowPct": 0.7906,
    "away_threePointFieldGoalsAttempted": 43.8,
    "away_threePointFieldGoalsMade": 17.6,
    "away_threePointPct": 0.4028,
    "away_overall_record": "36-16",
    "away_home_record": "16-10",
    "away_road_record": "20-6",
    "away_overall_record_win_rate": 0.692,
    "away_home_record_win_rate": 0.615,
    "away_road_record_win_rate": 0.769,
    "away_recent_win_rate": 0.6666666667,
    "away_recent_avg_score": 116.67,
    "away_recent_home_win_rate": 0.0,
    "away_recent_away_win_rate": 1.0,
    "away_leader_points": 28.8,
    "away_leader_rebounds": 8.6,
    "away_leader_assists": 8.2,
    "away_rest_days": 1.0,
    "home_vs_away_wins": 0.0,
    "home_vs_away_losses": 0.0,
    "home_vs_away_win_rate": 0.5
  },
  {
    "game_id": "401705315",
    "date": "2025-02-09T02:00:00.000Z",
    "season_year": 2025,
    "season_type": 2,
    "status": "STATUS_SCHEDULED",
    "home_team_id": "21",
    "home_team_name": "Suns",
    "home_team_score": 0,
    "away_team_id": "7",
    "away_team_name": "Nuggets",
    "away_team_score": 0,
    "home_rebounds": 42.4,
    "home_assists": 29.0,
    "home_fieldGoalsAttempted": 86.4,
    "home_fieldGoalsMade": 41.6,
    "home_fieldGoalPct": 0.4816,
    "home_freeThrowsAttempted": 24.8,
    "home_freeThrowsMade": 21.0,
    "home_freeThrowPct": 0.835,
    "home_threePointFieldGoalsAttempted": 41.2,
    "home_threePointFieldGoalsMade": 16.0,
    "home_threePointPct": 0.3858,
    "home_overall_record": "26-25",
    "home_home_record": "16-9",
    "home_road_record": "10-16",
    "home_overall_record_win_rate": 0.51,
    "home_home_record_win_rate": 0.64,
    "home_road_record_win_rate": 0.385,
    "home_recent_win_rate": 0.3333333333,
    "home_recent_avg_score": 121.0,
    "home_recent_home_win_rate": 1.0,
    "home_recent_away_win_rate": 0.0,
    "home_leader_points": 34.8,
    "home_leader_rebounds": 11.6,
    "home_leader_assists": 7.6,
    "home_rest_days": 0.0,
    "away_rebounds": 45.4,
    "away_assists": 33.8,
    "away_fieldGoalsAttempted": 89.0,
    "away_fieldGoalsMade": 48.4,
    "away_fieldGoalPct": 0.545,
    "away_freeThrowsAttempted": 20.0,
    "away_freeThrowsMade": 16.4,
    "away_freeThrowPct": 0.8312,
    "away_threePointFieldGoalsAttempted": 33.2,
    "away_threePointFieldGoalsMade": 11.8,
    "away_threePointPct": 0.3694,
    "away_overall_record": "33-19",
    "away_home_record": "17-8",
    "away_road_record": "16-11",
    "away_overall_record_win_rate": 0.635,
    "away_home_record_win_rate": 0.68,
    "away_road_record_win_rate": 0.593,
    "away_recent_win_rate": 1.0,
    "away_recent_avg_score": 127.0,
    "away_recent_home_win_rate": 1.0,
    "away_recent_away_win_rate": 0.0,
    "away_leader_points": 32.8,
    "away_leader_rebounds": 11.6,
    "away_leader_assists": 12.8,
    "away_rest_days": 1.0,
    "home_vs_away_wins": 1.0,
    "home_vs_away_losses": 1.0,
    "home_vs_away_win_rate": 0.5
  },
  {
    "game_id": "401705316",
    "date": "2025-02-09T03:00:00.000Z",
    "season_year": 2025,
    "season_type": 2,
    "status": "STATUS_SCHEDULED",
    "home_team_id": "23",
    "home_team_name": "Kings",
    "home_team_score": 0,
    "away_team_id": "3",
    "away_team_name": "Pelicans",
    "away_team_score": 0,
    "home_rebounds": 42.8,
    "home_assists": 25.2,
    "home_fieldGoalsAttempted": 90.0,
    "home_fieldGoalsMade": 40.4,
    "home_fieldGoalPct": 0.4506,
    "home_freeThrowsAttempted": 22.6,
    "home_freeThrowsMade": 17.6,
    "home_freeThrowPct": 0.7846,
    "home_threePointFieldGoalsAttempted": 33.2,
    "home_threePointFieldGoalsMade": 10.2,
    "home_threePointPct": 0.3228,
    "home_overall_record": "25-26",
    "home_home_record": "13-13",
    "home_road_record": "12-13",
    "home_overall_record_win_rate": 0.49,
    "home_home_record_win_rate": 0.5,
    "home_road_record_win_rate": 0.48,
    "home_recent_win_rate": 0.3333333333,
    "home_recent_avg_score": 109.67,
    "home_recent_home_win_rate": 0.0,
    "home_recent_away_win_rate": 0.5,
    "home_leader_points": 23.4,
    "home_leader_rebounds": 11.8,
    "home_leader_assists": 7.2,
    "home_rest_days": 1.0,
    "away_rebounds": 41.8,
    "away_assists": 24.2,
    "away_fieldGoalsAttempted": 91.2,
    "away_fieldGoalsMade": 43.0,
    "away_fieldGoalPct": 0.4704,
    "away_freeThrowsAttempted": 23.8,
    "away_freeThrowsMade": 18.8,
    "away_freeThrowPct": 0.7928,
    "away_threePointFieldGoalsAttempted": 32.6,
    "away_threePointFieldGoalsMade": 12.8,
    "away_threePointPct": 0.3844,
    "away_overall_record": "12-39",
    "away_home_record": "8-18",
    "away_road_record": "4-21",
    "away_overall_record_win_rate": 0.235,
    "away_home_record_win_rate": 0.308,
    "away_road_record_win_rate": 0.16,
    "away_recent_win_rate": 0.0,
    "away_recent_avg_score": 116.0,
    "away_recent_home_win_rate": 0.0,
    "away_recent_away_win_rate": 0.0,
    "away_leader_points": 34.4,
    "away_leader_rebounds": 9.4,
    "away_leader_assists": 7.2,
    "away_rest_days": 2.0,
    "home_vs_away_wins": 1.0,
    "home_vs_away_losses": 0.0,
    "home_vs_away_win_rate": 1.0
  },
  {
    "game_id": "401705317",
    "date": "2025-02-09T03:30:00.000Z",
    "season_year": 2025,
    "season_type": 2,
    "status": "STATUS_SCHEDULED",
    "home_team_id": "12",
    "home_team_name": "Clippers",
    "home_team_score": 0,
    "away_team_id": "26",
    "away_team_name": "Jazz",
    "away_team_score": 0,
    "home_rebounds": 45.4,
    "home_assists": 25.6,
    "home_fieldGoalsAttempted": 87.4,
    "home_fieldGoalsMade": 41.6,
    "home_fieldGoalPct": 0.4768,
    "home_freeThrowsAttempted": 20.2,
    "home_freeThrowsMade": 16.0,
    "home_freeThrowPct": 0.7894,
    "home_threePointFieldGoalsAttempted": 32.2,
    "home_threePointFieldGoalsMade": 12.2,
    "home_threePointPct": 0.3864,
    "home_overall_record": "28-23",
    "home_home_record": "17-10",
    "home_road_record": "11-13",
    "home_overall_record_win_rate": 0.549,
    "home_home_record_win_rate": 0.63,
    "home_road_record_win_rate": 0.458,
    "home_recent_win_rate": 0.0,
    "home_recent_avg_score": 105.67,
    "home_recent_home_win_rate": 0.0,
    "home_recent_away_win_rate": 0.0,
    "home_leader_points": 24.2,
    "home_leader_rebounds": 13.2,
    "home_leader_assists": 9.4,
    "home_rest_days": 1.0,
    "away_rebounds": 49.0,
    "away_assists": 27.4,
    "away_fieldGoalsAttempted": 92.2,
    "away_fieldGoalsMade": 42.6,
    "away_fieldGoalPct": 0.4662,
    "away_freeThrowsAttempted": 25.2,
    "away_freeThrowsMade": 20.4,
    "away_freeThrowPct": 0.8194,
    "away_threePointFieldGoalsAttempted": 38.2,
    "away_threePointFieldGoalsMade": 13.4,
    "away_threePointPct": 0.357,
    "away_overall_record": "12-38",
    "away_home_record": "5-18",
    "away_road_record": "7-20",
    "away_overall_record_win_rate": 0.24,
    "away_home_record_win_rate": 0.217,
    "away_road_record_win_rate": 0.259,
    "away_recent_win_rate": 0.3333333333,
    "away_recent_avg_score": 123.0,
    "away_recent_home_win_rate": 0.5,
    "away_recent_away_win_rate": 0.0,
    "away_leader_points": 23.6,
    "away_leader_rebounds": 15.2,
    "away_leader_assists": 10.0,
    "away_rest_days": 0.0,
    "home_vs_away_wins": 2.0,
    "home_vs_away_losses": 0.0,
    "home_vs_away_win_rate": 1.0
  }
]
